{"Program":{"Subprogram":{"Const Description":{"Terminal":"const","Const Defined":{"Const Defined":{"ID":"c1","Terminal_0":"=","Terminal_1":"2"},"Const Defined Any":{"Terminal":";"}}},"Var Description":{"Terminal":"var","Var Defineds":{"ID":"v1","ID Any":{"Terminal":",","ID":"v2","ID Any":{"Terminal":",","ID":"v3","ID Any":{"Terminal":",","ID":"v4","ID Any":{}}}},"Terminal":";"}},"Pocedure Descrition":{"Procedures":{"Procedure":{"Procesure Head":{"Terminal_0":"procedure","ID":"p1","Terminal_1":";"},"Subprogram":{"Const Description":{},"Var Description":{"Terminal":"var","Var Defineds":{"ID":"v5","ID Any":{},"Terminal":";"}},"Pocedure Descrition":{},"Statement":{"Complex":{"Terminal_0":"begin","Statement":{"Statement":{"Assign":{"ID":"v5","Terminal":":=","Expression":{"Items":{"Item":{"Factor":{"Terminal":"2"},"Factor Any":{}},"Item Any":{}}}}},"Statement Any":{"Terminal":";","Statement":{"Write":{"Terminal_0":"write","Terminal_1":"(","Expression":{"Items":{"Item":{"Factor":{"Terminal":"v5"},"Factor Any":{"Terminal":"/","Facotr":{"Terminal":"2"},"Factor Any":{}}},"Item Any":{"Terminal":"+","Item":{"Factor":{"Terminal":"2"},"Factor Any":{}},"Item Any":{"Terminal":"-","Item":{"Factor":{"Terminal":"1"},"Factor Any":{}},"Item Any":{}}}}},"Expression Any":{},"Terminal_2":")"}},"Statement Any":{"Terminal":";","Statement":{"While":{"Terminal_0":"while","Condition":{"Expression_0":{"Items":{"Item":{"Factor":{"Terminal":"v3"},"Factor Any":{}},"Item Any":{}}},"Terminal":"#","Expression_1":{"Items":{"Item":{"Factor":{"Terminal":"0"},"Factor Any":{}},"Item Any":{}}}},"Terminal_1":"do","Statement":{"Complex":{"Terminal_0":"begin","Statement":{"Statement":{"Assign":{"ID":"v4","Terminal":":=","Expression":{"Items":{"Item":{"Factor":{"Terminal":"v1"},"Factor Any":{"Terminal":"/","Facotr":{"Terminal":"v2"},"Factor Any":{}}},"Item Any":{}}}}},"Statement Any":{"Terminal":";","Statement":{"Assign":{"ID":"v3","Terminal":":=","Expression":{"Items":{"Item":{"Factor":{"Terminal":"v1"},"Factor Any":{}},"Item Any":{"Terminal":"-","Item":{"Factor":{"Terminal":"v4"},"Factor Any":{"Terminal":"*","Facotr":{"Terminal":"v2"},"Factor Any":{}}},"Item Any":{}}}}}},"Statement Any":{"Terminal":";","Statement":{"Assign":{"ID":"v1","Terminal":":=","Expression":{"Items":{"Item":{"Factor":{"Terminal":"v2"},"Factor Any":{}},"Item Any":{}}}}},"Statement Any":{"Terminal":";","Statement":{"Assign":{"ID":"v2","Terminal":":=","Expression":{"Items":{"Item":{"Factor":{"Terminal":"v3"},"Factor Any":{}},"Item Any":{}}}}},"Statement Any":{"Terminal":";","Statement":{},"Statement Any":{}}}}}},"Terminal_1":"end"}}}},"Statement Any":{"Terminal":";","Statement":{},"Statement Any":{}}}}},"Terminal_1":"end"}}},"Terminal":";"},"Procedure Any":{"Procedure":{"Procesure Head":{"Terminal_0":"procedure","ID":"p2","Terminal_1":";"},"Subprogram":{"Const Description":{"Terminal":"const","Const Defined":{"Const Defined":{"ID":"c2","Terminal_0":"=","Terminal_1":"2"},"Const Defined Any":{"Terminal":";"}}},"Var Description":{},"Pocedure Descrition":{"Procedures":{"Procedure":{"Procesure Head":{"Terminal_0":"procedure","ID":"p3","Terminal_1":";"},"Subprogram":{"Const Description":{},"Var Description":{},"Pocedure Descrition":{},"Statement":{"Complex":{"Terminal_0":"begin","Statement":{"Statement":{"Conditional":{"Terminal_0":"if","Condition":{"Expression_0":{"Items":{"Item":{"Factor":{"Terminal":"v1"},"Factor Any":{}},"Item Any":{}}},"Terminal":"#","Expression_1":{"Items":{"Item":{"Factor":{"Terminal":"1"},"Factor Any":{}},"Item Any":{}}}},"Terminal_1":"then","Statement":{"Complex":{"Terminal_0":"begin","Statement":{"Statement":{"Assign":{"ID":"v1","Terminal":":=","Expression":{"Items":{"Item":{"Factor":{"Terminal":"v1"},"Factor Any":{}},"Item Any":{"Terminal":"-","Item":{"Factor":{"Terminal":"1"},"Factor Any":{}},"Item Any":{}}}}}},"Statement Any":{"Terminal":";","Statement":{"Assign":{"ID":"v2","Terminal":":=","Expression":{"Items":{"Item":{"Factor":{"Terminal":"v2"},"Factor Any":{"Terminal":"*","Facotr":{"Terminal":"v1"},"Factor Any":{}}},"Item Any":{}}}}},"Statement Any":{"Terminal":";","Statement":{"Call":{"Terminal_0":"call","Terminal_1":"p3"}},"Statement Any":{"Terminal":";","Statement":{},"Statement Any":{}}}}},"Terminal_1":"end"}}}},"Statement Any":{"Terminal":";","Statement":{},"Statement Any":{}}},"Terminal_1":"end"}}},"Terminal":";"},"Procedure Any":{}}},"Statement":{"Complex":{"Terminal_0":"begin","Statement":{"Statement":{"Call":{"Terminal_0":"call","Terminal_1":"p3"}},"Statement Any":{"Terminal":";","Statement":{"Conditional":{"Terminal_0":"if","Condition":{"Terminal":"odd","Expression":{"Items":{"Item":{"Factor":{"Terminal":"c2"},"Factor Any":{}},"Item Any":{}}}},"Terminal_1":"then","Statement":{"Write":{"Terminal_0":"write","Terminal_1":"(","Expression":{"Items":{"Item":{"Factor":{"Terminal":"c2"},"Factor Any":{}},"Item Any":{}}},"Expression Any":{},"Terminal_2":")"}}}},"Statement Any":{"Terminal":";","Statement":{"Conditional":{"Terminal_0":"if","Condition":{"Expression_0":{"Items":{"Item":{"Factor":{"Terminal":"c2"},"Factor Any":{}},"Item Any":{}}},"Terminal":"=","Expression_1":{"Items":{"Item":{"Factor":{"Terminal":"2"},"Factor Any":{}},"Item Any":{}}}},"Terminal_1":"then","Statement":{"Write":{"Terminal_0":"write","Terminal_1":"(","Expression":{"Items":{"Item":{"Factor":{"Terminal":"c2"},"Factor Any":{}},"Item Any":{"Terminal":"+","Item":{"Factor":{"Terminal":"1"},"Factor Any":{}},"Item Any":{}}}},"Expression Any":{},"Terminal_2":")"}}}},"Statement Any":{}}}},"Terminal_1":"end"}}},"Terminal":";"},"Procesure Any":{}}}},"Statement":{"Complex":{"Terminal_0":"begin","Statement":{"Statement":{"Read":{"Terminal_0":"read","Terminal_1":"(","ID":"v1","ID Any":{"Terminal":",","ID":"v2","ID Any":{}},"Terminal_2":")"}},"Statement Any":{"Terminal":";","Statement":{"Conditional":{"Terminal_0":"if","Condition":{"Expression_0":{"Items":{"Item":{"Factor":{"Terminal":"v1"},"Factor Any":{}},"Item Any":{}}},"Terminal":"<","Expression_1":{"Items":{"Item":{"Factor":{"Terminal":"v2"},"Factor Any":{}},"Item Any":{}}}},"Terminal_1":"then","Statement":{"Complex":{"Terminal_0":"begin","Statement":{"Statement":{"Assign":{"ID":"v3","Terminal":":=","Expression":{"Items":{"Item":{"Factor":{"Terminal":"v1"},"Factor Any":{}},"Item Any":{}}}}},"Statement Any":{"Terminal":";","Statement":{"Assign":{"ID":"v1","Terminal":":=","Expression":{"Items":{"Item":{"Factor":{"Terminal":"v2"},"Factor Any":{}},"Item Any":{}}}}},"Statement Any":{"Terminal":";","Statement":{"Assign":{"ID":"v2","Terminal":":=","Expression":{"Items":{"Item":{"Factor":{"Terminal":"v3"},"Factor Any":{}},"Item Any":{}}}}},"Statement Any":{"Terminal":";","Statement":{},"Statement Any":{}}}}},"Terminal_1":"end"}}}},"Statement Any":{"Terminal":";","Statement":{"Complex":{"Terminal_0":"begin","Statement":{"Statement":{},"Statement Any":{"Terminal":";","Statement":{"Assign":{"ID":"v3","Terminal":":=","Expression":{"Items":{"Item":{"Factor":{"Terminal":"1"},"Factor Any":{}},"Item Any":{}}}}},"Statement Any":{"Terminal":";","Statement":{"Call":{"Terminal_0":"call","Terminal_1":"p1"}},"Statement Any":{"Terminal":";","Statement":{"Write":{"Terminal_0":"write","Terminal_1":"(","Expression":{"Items":{"Item":{"Factor":{"Terminal":"c1"},"Factor Any":{}},"Item Any":{}}},"Expression Any":{"Terminal":",","Expression":{"Items":{"Item":{"Factor":{"Terminal":"c1"},"Factor Any":{"Terminal":"*","Facotr":{"Terminal":"v1"},"Factor Any":{}}},"Item Any":{}}},"Expression Any":{"Terminal":",","Expression":{"Items":{"Item":{"Factor":{"Terminal":"c1"},"Factor Any":{"Terminal":"*","Facotr":{"Terminal":"v1"},"Factor Any":{"Terminal":"/","Facotr":{"Terminal":"2"},"Factor Any":{}}}},"Item Any":{}}},"Expression Any":{}}},"Terminal_2":")"}},"Statement Any":{"Terminal":";","Statement":{},"Statement Any":{}}}}}},"Terminal_1":"end"}},"Statement Any":{"Terminal":";","Statement":{"Read":{"Terminal_0":"read","Terminal_1":"(","ID":"v1","ID Any":{},"Terminal_2":")"}},"Statement Any":{"Terminal":";","Statement":{"Assign":{"ID":"v2","Terminal":":=","Expression":{"Items":{"Item":{"Factor":{"Terminal":"v1"},"Factor Any":{}},"Item Any":{}}}}},"Statement Any":{"Terminal":";","Statement":{"Call":{"Terminal_0":"call","Terminal_1":"p2"}},"Statement Any":{"Terminal":";","Statement":{"Write":{"Terminal_0":"write","Terminal_1":"(","Expression":{"Items":{"Item":{"Factor":{"Terminal":"v2"},"Factor Any":{}},"Item Any":{}}},"Expression Any":{},"Terminal_2":")"}},"Statement Any":{"Terminal":";","Statement":{},"Statement Any":{}}}}}}}}},"Terminal_1":"end"}}},"Terminal":"."}}
